<PAMDataset>
  <Metadata domain="Esri">
    <MDI key="PyramidResamplingType">NEAREST</MDI>
  </Metadata>
  <PAMRasterBand band="1">
    <Histograms>
      <HistItem>
        <HistMin>-137.75</HistMin>
        <HistMax>5217.25</HistMax>
        <BucketCount>256</BucketCount>
        <IncludeOutOfRange>1</IncludeOutOfRange>
        <Approximate>0</Approximate>
        <HistCounts>1|2|15|62|47|99|34441|40776|30842|28501|28583|28944|27898|33096|32038|28819|27373|26195|28024|28771|30245|32329|24383|23014|21236|19900|18180|16950|16495|14864|13486|12991|11971|11574|11512|11156|9594|9211|8956|8431|7837|7356|7124|6768|6272|6209|5925|6040|5933|6091|5822|5235|4953|4875|4773|4658|4533|4579|4567|4513|4290|4399|4547|4846|4967|4582|4533|4810|4566|4462|4419|4402|4288|4240|4053|4072|4090|3981|3975|4001|3684|3623|3541|3416|3211|3249|3152|3219|3156|2972|2900|2956|2959|3369|3031|2763|2813|2708|2726|2598|2987|2981|2771|2521|2568|2528|2478|2731|2893|2441|2210|2132|2052|2048|2111|2703|2143|1796|1709|1696|1745|1795|2555|2117|1573|1405|1411|1282|1277|1721|1411|1044|979|901|891|885|986|1248|1016|931|765|813|784|865|1337|916|753|675|624|629|656|1129|1333|740|347|248|214|224|186|156|126|92|93|91|86|84|80|77|75|73|56|58|58|59|44|52|52|39|39|40|35|22|19|27|26|15|14|16|9|6|9|8|10|10|8|8|4|5|4|2|3|3|0|4|6|2|4|5|4|3|1|2|5|2|0|1|1|1|0|1|0|1|1|0|2|1|2|1|0|0|0|0|1|0|0|0|0|1|1|0|0|0|0|0|0|0|1|0|0|0|0|0|0|0|0|1</HistCounts>
      </HistItem>
    </Histograms>
    <Metadata>
      <MDI key="RepresentationType">ATHEMATIC</MDI>
      <MDI key="STATISTICS_COVARIANCES">501904.2049238758</MDI>
      <MDI key="STATISTICS_MAXIMUM">5217.25</MDI>
      <MDI key="STATISTICS_MEAN">673.11373912159</MDI>
      <MDI key="STATISTICS_MINIMUM">-137.75</MDI>
      <MDI key="STATISTICS_SKIPFACTORX">1</MDI>
      <MDI key="STATISTICS_SKIPFACTORY">1</MDI>
      <MDI key="STATISTICS_STDDEV">708.45197785303</MDI>
    </Metadata>
  </PAMRasterBand>
</PAMDataset>
